neurogenome/__init__.py
neurogenome/builders.py
neurogenome/evolution.py
neurogenome/file_handler.py
neurogenome/genome.py
neurogenome/macromutations.py
neurogenome-0.1.4.dist-info/LICENSE
neurogenome-0.1.4.dist-info/WHEEL
neurogenome-0.1.4.dist-info/METADATA
neurogenome-0.1.4.dist-info/RECORD
