Metadata-Version: 2.1
Name: neurogenome
Version: 0.1.4
Summary: A universal API for create artificial neural networks with a genetic code.
Home-page: https://github.com/Aiyyskhan/NeuroGenome
License: MIT
Author: Aiyyskhan Alekseev
Author-email: aiyykhan@gmail.com
Requires-Python: >=3.7,<4.0
Classifier: License :: OSI Approved :: MIT License
Classifier: Programming Language :: Python :: 3
Classifier: Programming Language :: Python :: 3.10
Classifier: Programming Language :: Python :: 3.7
Classifier: Programming Language :: Python :: 3.8
Classifier: Programming Language :: Python :: 3.9
Requires-Dist: h5py (>=2.10,<3.0)
Requires-Dist: numpy (>=1.21,<2.0)
Project-URL: Repository, https://github.com/Aiyyskhan/NeuroGenome
